<root>
    <row>
        <id>1106</id>
        <id_padre>1714</id_padre>
        <nome>Modifica Utente</nome>
        <img>pencil.png</img>
        <icons>fa fa-pencil</icons>
        <ordine />
        <obj>user</obj>
        <act>editUser</act>
        <funzione>editTablename</funzione>
        <subtitle />
        <txt />
        <query>a:0:{}</query>
        <order_by>a:0:{}</order_by>
        <load_tables>liveuser_users</load_tables>
        <fieldstorender>auth_user_id,handle,passwd,email,nome,cognome,ente,matr</fieldstorender>
        <hiddenfields />
        <defaults>a:0:{}</defaults>
        <visibility />
        <processed />
        <js_head />
        <js_foot />
        <id_approvaz />
        <handle />
        <datemod />
        <last_stato />
        <querystr_keys>auth_user_id</querystr_keys>
    </row>
</root>
